pacificescloud.py
pacifices/__init__.py
pacifices/cloud/__init__.py
pacifices/cloud/server.py
pacifices_cloud-0.1.0.dist-info/LICENSE
pacifices_cloud-0.1.0.dist-info/METADATA
pacifices_cloud-0.1.0.dist-info/WHEEL
pacifices_cloud-0.1.0.dist-info/entry_points.txt
pacifices_cloud-0.1.0.dist-info/top_level.txt
pacifices_cloud-0.1.0.dist-info/RECORD
