Metadata-Version: 2.1
Name: pacifices-cloud
Version: 0.1.0
Summary: A CLI tool for managing your https://pacifices.cloud servers
Home-page: https://github.com/sktan/pacifices-cloud-cli
Author: Steven Tan
Author-email: git@sktan.com
License: UNKNOWN
Keywords: pacifices cloud pacifices.cloud
Platform: UNKNOWN
Classifier: Development Status :: 4 - Beta
Classifier: Environment :: Console
Classifier: Operating System :: OS Independent
Classifier: License :: OSI Approved :: MIT License
Classifier: Programming Language :: Python :: 3 :: Only
Classifier: Programming Language :: Python :: 3.6
Classifier: Programming Language :: Python :: 3.7
Classifier: Programming Language :: Python :: 3.8
Classifier: Topic :: Utilities
Classifier: Typing :: Typed
Requires-Python: >=3.6
Requires-Dist: requests (==2.23.0)
Requires-Dist: python-dotenv (==0.13.0)
